two_goats_one_car/__init__.py
two_goats_one_car/__main__.py
two_goats_one_car/monty.py
two_goats_one_car/results.py
two_goats_one_car-1.0.2.dist-info/entry_points.txt
two_goats_one_car-1.0.2.dist-info/LICENSE
two_goats_one_car-1.0.2.dist-info/METADATA
two_goats_one_car-1.0.2.dist-info/WHEEL
two_goats_one_car-1.0.2.dist-info/RECORD
